LICENSE
README.md
setup.cfg
setup.py
nextcord/ext/ipc/__init__.py
nextcord/ext/ipc/client.py
nextcord/ext/ipc/errors.py
nextcord/ext/ipc/server.py
nextcord_ext_ipc_dev.egg-info/PKG-INFO
nextcord_ext_ipc_dev.egg-info/SOURCES.txt
nextcord_ext_ipc_dev.egg-info/dependency_links.txt
nextcord_ext_ipc_dev.egg-info/requires.txt
nextcord_ext_ipc_dev.egg-info/top_level.txt